.coveragerc
.gitignore
AUTHORS.rst
CHANGELOG.rst
README.md
requirements.txt
setup.cfg
setup.py
test-requirements.txt
wercker.yml
docs/Makefile
docs/authors.rst
docs/changelog.rst
docs/conf.py
docs/index.rst
docs/license.rst
docs/_static/.gitignore
src/clustaar/__init__.py
src/clustaar.sqlalchemy.egg-info/PKG-INFO
src/clustaar.sqlalchemy.egg-info/SOURCES.txt
src/clustaar.sqlalchemy.egg-info/dependency_links.txt
src/clustaar.sqlalchemy.egg-info/not-zip-safe
src/clustaar.sqlalchemy.egg-info/requires.txt
src/clustaar.sqlalchemy.egg-info/top_level.txt
src/clustaar/sqlalchemy/__init__.py
src/clustaar/sqlalchemy/constants.py
src/clustaar/sqlalchemy/database.py
src/clustaar/sqlalchemy/schema.py
src/clustaar/sqlalchemy/sql_alchemy_conditions_translator.py
src/clustaar/sqlalchemy/table.py
tests/conftest.py
tests/fixtures/__init__.py
tests/fixtures/tables.py
tests/sqlalchemy/test_database.py
tests/sqlalchemy/test_sql_alchemy_conditions_translator.py
tests/sqlalchemy/test_table.py
tests/utils/__init__.py