Metadata-Version: 2.1
Name: clustaar.sqlalchemy
Version: 0.1.0
Summary: A lightweight postgresql framework based upon sqlachemy
Home-page: https://github.com/Clustaar/clustaar.sqlalchemy
Author: Axel schäfers
Author-email: axel.schafers@gmail.com
License: mit
Platform: any
Classifier: Development Status :: 4 - Beta
Classifier: Programming Language :: Python
Provides-Extra: testing
